{
    "traces_file": "./temp_traces/tomm19_hd_fs_traces_086.json",
    "abr_algorithm": "throughput",
    "manifest_file": "/home/jonathan/prg/ex/sabre/manifests/green_abr_manifest.json",
    "bitrate_choices": [
        {
            "time_ms": 0,
            "bitrate_kbps": 150
        },
        {
            "time_ms": 32.871669455528384,
            "bitrate_kbps": 12000
        },
        {
            "time_ms": 1082.605225897799,
            "bitrate_kbps": 12000
        },
        {
            "time_ms": 2132.33878234007,
            "bitrate_kbps": 12000
        },
        {
            "time_ms": 3182.0723387823405,
            "bitrate_kbps": 12000
        },
        {
            "time_ms": 4231.805895224611,
            "bitrate_kbps": 12000
        },
        {
            "time_ms": 5230.506902729477,
            "bitrate_kbps": 12000
        },
        {
            "time_ms": 6093.5883654758145,
            "bitrate_kbps": 12000
        },
        {
            "time_ms": 6956.669828222152,
            "bitrate_kbps": 12000
        },
        {
            "time_ms": 7819.75129096849,
            "bitrate_kbps": 12000
        },
        {
            "time_ms": 8682.832753714829,
            "bitrate_kbps": 12000
        },
        {
            "time_ms": 9545.914216461166,
            "bitrate_kbps": 12000
        },
        {
            "time_ms": 10750.766056229044,
            "bitrate_kbps": 12000
        },
        {
            "time_ms": 12318.354397730205,
            "bitrate_kbps": 12000
        },
        {
            "time_ms": 13885.942739231366,
            "bitrate_kbps": 12000
        },
        {
            "time_ms": 15301.705559368567,
            "bitrate_kbps": 12000
        },
        {
            "time_ms": 16351.218256691835,
            "bitrate_kbps": 12000
        },
        {
            "time_ms": 17400.7309540151,
            "bitrate_kbps": 12000
        },
        {
            "time_ms": 18450.24365133837,
            "bitrate_kbps": 12000
        },
        {
            "time_ms": 19499.756348661635,
            "bitrate_kbps": 12000
        },
        {
            "time_ms": 20660.94874309606,
            "bitrate_kbps": 12000
        },
        {
            "time_ms": 21919.786300521344,
            "bitrate_kbps": 12000
        },
        {
            "time_ms": 23178.623857946626,
            "bitrate_kbps": 12000
        },
        {
            "time_ms": 24437.46141537191,
            "bitrate_kbps": 12000
        },
        {
            "time_ms": 25710.155304027376,
            "bitrate_kbps": 12000
        },
        {
            "time_ms": 27032.87166945553,
            "bitrate_kbps": 12000
        },
        {
            "time_ms": 29032.87166945553,
            "bitrate_kbps": 12000
        },
        {
            "time_ms": 31032.87166945553,
            "bitrate_kbps": 12000
        },
        {
            "time_ms": 33032.87166945553,
            "bitrate_kbps": 12000
        },
        {
            "time_ms": 35032.87166945553,
            "bitrate_kbps": 12000
        },
        {
            "time_ms": 37032.87166945553,
            "bitrate_kbps": 12000
        },
        {
            "time_ms": 39032.87166945553,
            "bitrate_kbps": 12000
        },
        {
            "time_ms": 41032.87166945553,
            "bitrate_kbps": 12000
        },
        {
            "time_ms": 43032.87166945553,
            "bitrate_kbps": 12000
        },
        {
            "time_ms": 45032.87166945553,
            "bitrate_kbps": 12000
        },
        {
            "time_ms": 47032.87166945553,
            "bitrate_kbps": 12000
        },
        {
            "time_ms": 49032.87166945553,
            "bitrate_kbps": 12000
        },
        {
            "time_ms": 51032.87166945553,
            "bitrate_kbps": 12000
        },
        {
            "time_ms": 53032.87166945553,
            "bitrate_kbps": 12000
        },
        {
            "time_ms": 55032.87166945553,
            "bitrate_kbps": 12000
        },
        {
            "time_ms": 57032.87166945553,
            "bitrate_kbps": 12000
        },
        {
            "time_ms": 59032.87166945553,
            "bitrate_kbps": 12000
        },
        {
            "time_ms": 61032.87166945553,
            "bitrate_kbps": 12000
        },
        {
            "time_ms": 63032.87166945553,
            "bitrate_kbps": 12000
        },
        {
            "time_ms": 65032.87166945553,
            "bitrate_kbps": 12000
        },
        {
            "time_ms": 67032.87166945553,
            "bitrate_kbps": 12000
        },
        {
            "time_ms": 69032.87166945553,
            "bitrate_kbps": 12000
        },
        {
            "time_ms": 71032.87166945553,
            "bitrate_kbps": 12000
        },
        {
            "time_ms": 73032.87166945553,
            "bitrate_kbps": 12000
        },
        {
            "time_ms": 75032.87166945553,
            "bitrate_kbps": 12000
        },
        {
            "time_ms": 77032.87166945553,
            "bitrate_kbps": 12000
        },
        {
            "time_ms": 79032.87166945553,
            "bitrate_kbps": 12000
        },
        {
            "time_ms": 81032.87166945555,
            "bitrate_kbps": 12000
        },
        {
            "time_ms": 83554.43514662878,
            "bitrate_kbps": 12000
        },
        {
            "time_ms": 85854.43514662878,
            "bitrate_kbps": 12000
        },
        {
            "time_ms": 86354.43514662878,
            "bitrate_kbps": 12000
        },
        {
            "time_ms": 86854.43514662878,
            "bitrate_kbps": 12000
        },
        {
            "time_ms": 87354.43514662878,
            "bitrate_kbps": 12000
        },
        {
            "time_ms": 87854.43514662878,
            "bitrate_kbps": 12000
        },
        {
            "time_ms": 88354.43514662878,
            "bitrate_kbps": 12000
        },
        {
            "time_ms": 88854.43514662878,
            "bitrate_kbps": 12000
        },
        {
            "time_ms": 89354.43514662878,
            "bitrate_kbps": 12000
        },
        {
            "time_ms": 89854.43514662878,
            "bitrate_kbps": 12000
        },
        {
            "time_ms": 90354.43514662878,
            "bitrate_kbps": 12000
        },
        {
            "time_ms": 90854.43514662878,
            "bitrate_kbps": 12000
        },
        {
            "time_ms": 91354.43514662878,
            "bitrate_kbps": 12000
        },
        {
            "time_ms": 91854.43514662878,
            "bitrate_kbps": 12000
        },
        {
            "time_ms": 92354.43514662878,
            "bitrate_kbps": 12000
        },
        {
            "time_ms": 92854.43514662878,
            "bitrate_kbps": 12000
        },
        {
            "time_ms": 93354.43514662878,
            "bitrate_kbps": 12000
        },
        {
            "time_ms": 93854.43514662878,
            "bitrate_kbps": 12000
        },
        {
            "time_ms": 94354.43514662878,
            "bitrate_kbps": 12000
        },
        {
            "time_ms": 94854.43514662878,
            "bitrate_kbps": 12000
        },
        {
            "time_ms": 95354.43514662878,
            "bitrate_kbps": 12000
        },
        {
            "time_ms": 95854.43514662878,
            "bitrate_kbps": 12000
        },
        {
            "time_ms": 96354.43514662878,
            "bitrate_kbps": 12000
        },
        {
            "time_ms": 96854.43514662878,
            "bitrate_kbps": 12000
        },
        {
            "time_ms": 97354.43514662878,
            "bitrate_kbps": 12000
        },
        {
            "time_ms": 97854.43514662878,
            "bitrate_kbps": 12000
        },
        {
            "time_ms": 98354.43514662878,
            "bitrate_kbps": 12000
        },
        {
            "time_ms": 98854.43514662878,
            "bitrate_kbps": 12000
        },
        {
            "time_ms": 99354.43514662878,
            "bitrate_kbps": 12000
        },
        {
            "time_ms": 99854.43514662878,
            "bitrate_kbps": 12000
        },
        {
            "time_ms": 100354.43514662878,
            "bitrate_kbps": 12000
        },
        {
            "time_ms": 100854.43514662878,
            "bitrate_kbps": 12000
        },
        {
            "time_ms": 101354.43514662878,
            "bitrate_kbps": 12000
        },
        {
            "time_ms": 101854.43514662878,
            "bitrate_kbps": 12000
        },
        {
            "time_ms": 102354.43514662878,
            "bitrate_kbps": 12000
        },
        {
            "time_ms": 102854.43514662878,
            "bitrate_kbps": 12000
        },
        {
            "time_ms": 103354.43514662878,
            "bitrate_kbps": 9000
        },
        {
            "time_ms": 103854.43514662878,
            "bitrate_kbps": 6000
        },
        {
            "time_ms": 104354.43514662878,
            "bitrate_kbps": 6000
        },
        {
            "time_ms": 104854.43514662878,
            "bitrate_kbps": 4300
        },
        {
            "time_ms": 105354.43514662878,
            "bitrate_kbps": 1850
        },
        {
            "time_ms": 107392.98397368824,
            "bitrate_kbps": 4300
        },
        {
            "time_ms": 107892.98397368824,
            "bitrate_kbps": 2850
        },
        {
            "time_ms": 111041.96755073404,
            "bitrate_kbps": 2850
        },
        {
            "time_ms": 114230.39445456951,
            "bitrate_kbps": 1850
        },
        {
            "time_ms": 116539.9211681536,
            "bitrate_kbps": 1200
        },
        {
            "time_ms": 118131.63040194534,
            "bitrate_kbps": 1200
        },
        {
            "time_ms": 119723.3396357371,
            "bitrate_kbps": 1200
        },
        {
            "time_ms": 121365.11191282838,
            "bitrate_kbps": 1200
        },
        {
            "time_ms": 123016.65508074136,
            "bitrate_kbps": 1200
        },
        {
            "time_ms": 124668.19824865434,
            "bitrate_kbps": 1200
        },
        {
            "time_ms": 126462.95374813152,
            "bitrate_kbps": 1200
        },
        {
            "time_ms": 128291.54455446158,
            "bitrate_kbps": 1200
        },
        {
            "time_ms": 130107.42562248687,
            "bitrate_kbps": 1200
        },
        {
            "time_ms": 131744.67629634132,
            "bitrate_kbps": 1200
        },
        {
            "time_ms": 133381.92697019578,
            "bitrate_kbps": 1200
        },
        {
            "time_ms": 135015.77584466216,
            "bitrate_kbps": 1200
        },
        {
            "time_ms": 136366.1527847952,
            "bitrate_kbps": 1200
        },
        {
            "time_ms": 137716.52972492826,
            "bitrate_kbps": 1200
        },
        {
            "time_ms": 139066.90666506128,
            "bitrate_kbps": 1200
        },
        {
            "time_ms": 140675.1386760274,
            "bitrate_kbps": 1200
        },
        {
            "time_ms": 142847.60504374042,
            "bitrate_kbps": 1200
        },
        {
            "time_ms": 145001.0575382181,
            "bitrate_kbps": 750
        },
        {
            "time_ms": 145091.93930742706,
            "bitrate_kbps": 1200
        },
        {
            "time_ms": 145225.3501381614,
            "bitrate_kbps": 1850
        },
        {
            "time_ms": 145420.1918355435,
            "bitrate_kbps": 1850
        },
        {
            "time_ms": 145615.0335329256,
            "bitrate_kbps": 1850
        },
        {
            "time_ms": 145809.8752303077,
            "bitrate_kbps": 1850
        },
        {
            "time_ms": 146004.7169276898,
            "bitrate_kbps": 2850
        },
        {
            "time_ms": 146294.06765068384,
            "bitrate_kbps": 2850
        },
        {
            "time_ms": 146583.41837367788,
            "bitrate_kbps": 2850
        },
        {
            "time_ms": 147539.9211681536,
            "bitrate_kbps": 2850
        },
        {
            "time_ms": 149539.9211681536,
            "bitrate_kbps": 4300
        },
        {
            "time_ms": 151539.9211681536,
            "bitrate_kbps": 4300
        },
        {
            "time_ms": 153539.9211681536,
            "bitrate_kbps": 4300
        },
        {
            "time_ms": 155539.9211681536,
            "bitrate_kbps": 6000
        },
        {
            "time_ms": 157539.9211681536,
            "bitrate_kbps": 6000
        },
        {
            "time_ms": 159539.9211681536,
            "bitrate_kbps": 6000
        },
        {
            "time_ms": 161539.9211681536,
            "bitrate_kbps": 6000
        },
        {
            "time_ms": 163539.92116815364,
            "bitrate_kbps": 6000
        },
        {
            "time_ms": 165539.92116815364,
            "bitrate_kbps": 9000
        },
        {
            "time_ms": 167539.92116815364,
            "bitrate_kbps": 9000
        },
        {
            "time_ms": 169539.92116815364,
            "bitrate_kbps": 9000
        },
        {
            "time_ms": 171539.92116815364,
            "bitrate_kbps": 9000
        },
        {
            "time_ms": 173539.92116815364,
            "bitrate_kbps": 12000
        },
        {
            "time_ms": 175539.92116815364,
            "bitrate_kbps": 12000
        },
        {
            "time_ms": 177539.92116815364,
            "bitrate_kbps": 12000
        },
        {
            "time_ms": 179539.92116815364,
            "bitrate_kbps": 12000
        },
        {
            "time_ms": 181539.92116815364,
            "bitrate_kbps": 12000
        },
        {
            "time_ms": 183539.92116815364,
            "bitrate_kbps": 12000
        },
        {
            "time_ms": 185539.92116815364,
            "bitrate_kbps": 12000
        },
        {
            "time_ms": 187902.07008978925,
            "bitrate_kbps": 12000
        },
        {
            "time_ms": 190133.37860042715,
            "bitrate_kbps": 12000
        },
        {
            "time_ms": 191539.92116815364,
            "bitrate_kbps": 12000
        },
        {
            "time_ms": 193539.92116815364,
            "bitrate_kbps": 12000
        },
        {
            "time_ms": 195539.92116815364,
            "bitrate_kbps": 12000
        },
        {
            "time_ms": 197539.92116815364,
            "bitrate_kbps": 12000
        },
        {
            "time_ms": 199539.92116815364,
            "bitrate_kbps": 12000
        },
        {
            "time_ms": 201539.9211681536,
            "bitrate_kbps": 12000
        },
        {
            "time_ms": 203539.9211681536,
            "bitrate_kbps": 12000
        },
        {
            "time_ms": 205539.9211681536,
            "bitrate_kbps": 12000
        },
        {
            "time_ms": 207539.9211681536,
            "bitrate_kbps": 12000
        },
        {
            "time_ms": 209539.9211681536,
            "bitrate_kbps": 12000
        },
        {
            "time_ms": 211539.9211681536,
            "bitrate_kbps": 12000
        },
        {
            "time_ms": 213539.9211681536,
            "bitrate_kbps": 12000
        },
        {
            "time_ms": 215539.9211681536,
            "bitrate_kbps": 12000
        },
        {
            "time_ms": 217539.9211681536,
            "bitrate_kbps": 12000
        },
        {
            "time_ms": 219539.9211681536,
            "bitrate_kbps": 12000
        },
        {
            "time_ms": 221539.9211681536,
            "bitrate_kbps": 12000
        },
        {
            "time_ms": 223539.9211681536,
            "bitrate_kbps": 12000
        },
        {
            "time_ms": 225539.9211681536,
            "bitrate_kbps": 12000
        },
        {
            "time_ms": 227539.9211681536,
            "bitrate_kbps": 12000
        },
        {
            "time_ms": 229539.9211681536,
            "bitrate_kbps": 12000
        },
        {
            "time_ms": 231539.9211681536,
            "bitrate_kbps": 12000
        },
        {
            "time_ms": 233539.9211681536,
            "bitrate_kbps": 12000
        },
        {
            "time_ms": 235539.9211681536,
            "bitrate_kbps": 12000
        },
        {
            "time_ms": 237539.9211681536,
            "bitrate_kbps": 12000
        },
        {
            "time_ms": 239539.9211681536,
            "bitrate_kbps": 12000
        },
        {
            "time_ms": 241539.9211681536,
            "bitrate_kbps": 12000
        },
        {
            "time_ms": 243539.9211681536,
            "bitrate_kbps": 12000
        },
        {
            "time_ms": 245539.9211681536,
            "bitrate_kbps": 12000
        },
        {
            "time_ms": 247539.9211681536,
            "bitrate_kbps": 12000
        },
        {
            "time_ms": 249539.9211681536,
            "bitrate_kbps": 12000
        },
        {
            "time_ms": 251539.9211681536,
            "bitrate_kbps": 12000
        },
        {
            "time_ms": 253539.9211681536,
            "bitrate_kbps": 12000
        },
        {
            "time_ms": 255539.9211681536,
            "bitrate_kbps": 12000
        },
        {
            "time_ms": 257539.9211681536,
            "bitrate_kbps": 12000
        },
        {
            "time_ms": 259539.9211681536,
            "bitrate_kbps": 12000
        },
        {
            "time_ms": 261539.9211681536,
            "bitrate_kbps": 12000
        },
        {
            "time_ms": 263539.92116815364,
            "bitrate_kbps": 12000
        },
        {
            "time_ms": 265539.92116815364,
            "bitrate_kbps": 12000
        },
        {
            "time_ms": 266039.92116815364,
            "bitrate_kbps": 12000
        },
        {
            "time_ms": 266539.92116815364,
            "bitrate_kbps": 12000
        },
        {
            "time_ms": 267039.92116815364,
            "bitrate_kbps": 12000
        },
        {
            "time_ms": 267539.92116815364,
            "bitrate_kbps": 12000
        },
        {
            "time_ms": 268039.92116815364,
            "bitrate_kbps": 12000
        },
        {
            "time_ms": 268539.92116815364,
            "bitrate_kbps": 12000
        },
        {
            "time_ms": 269039.92116815364,
            "bitrate_kbps": 12000
        },
        {
            "time_ms": 269539.92116815364,
            "bitrate_kbps": 12000
        },
        {
            "time_ms": 270039.92116815364,
            "bitrate_kbps": 12000
        },
        {
            "time_ms": 270539.92116815364,
            "bitrate_kbps": 12000
        },
        {
            "time_ms": 271039.92116815364,
            "bitrate_kbps": 12000
        },
        {
            "time_ms": 271539.92116815364,
            "bitrate_kbps": 12000
        },
        {
            "time_ms": 272039.92116815364,
            "bitrate_kbps": 12000
        },
        {
            "time_ms": 272539.92116815364,
            "bitrate_kbps": 12000
        },
        {
            "time_ms": 273039.92116815364,
            "bitrate_kbps": 12000
        },
        {
            "time_ms": 273539.92116815364,
            "bitrate_kbps": 12000
        },
        {
            "time_ms": 274039.92116815364,
            "bitrate_kbps": 12000
        },
        {
            "time_ms": 274539.92116815364,
            "bitrate_kbps": 12000
        },
        {
            "time_ms": 275039.92116815364,
            "bitrate_kbps": 12000
        },
        {
            "time_ms": 275539.92116815364,
            "bitrate_kbps": 12000
        },
        {
            "time_ms": 276039.92116815364,
            "bitrate_kbps": 12000
        },
        {
            "time_ms": 276539.92116815364,
            "bitrate_kbps": 12000
        },
        {
            "time_ms": 277039.92116815364,
            "bitrate_kbps": 12000
        },
        {
            "time_ms": 277539.92116815364,
            "bitrate_kbps": 12000
        },
        {
            "time_ms": 278039.92116815364,
            "bitrate_kbps": 12000
        },
        {
            "time_ms": 278539.92116815364,
            "bitrate_kbps": 12000
        },
        {
            "time_ms": 279039.92116815364,
            "bitrate_kbps": 12000
        },
        {
            "time_ms": 279539.92116815364,
            "bitrate_kbps": 12000
        },
        {
            "time_ms": 280039.92116815364,
            "bitrate_kbps": 12000
        },
        {
            "time_ms": 280539.92116815364,
            "bitrate_kbps": 12000
        },
        {
            "time_ms": 281039.92116815364,
            "bitrate_kbps": 12000
        },
        {
            "time_ms": 281539.92116815364,
            "bitrate_kbps": 12000
        },
        {
            "time_ms": 282039.92116815364,
            "bitrate_kbps": 12000
        },
        {
            "time_ms": 282539.92116815364,
            "bitrate_kbps": 12000
        },
        {
            "time_ms": 283039.92116815364,
            "bitrate_kbps": 12000
        },
        {
            "time_ms": 283539.92116815364,
            "bitrate_kbps": 12000
        },
        {
            "time_ms": 284039.92116815364,
            "bitrate_kbps": 12000
        },
        {
            "time_ms": 284539.92116815364,
            "bitrate_kbps": 12000
        },
        {
            "time_ms": 285039.92116815364,
            "bitrate_kbps": 12000
        },
        {
            "time_ms": 285539.92116815364,
            "bitrate_kbps": 12000
        },
        {
            "time_ms": 286039.92116815364,
            "bitrate_kbps": 12000
        },
        {
            "time_ms": 286539.92116815364,
            "bitrate_kbps": 12000
        },
        {
            "time_ms": 287039.92116815364,
            "bitrate_kbps": 9000
        },
        {
            "time_ms": 287539.92116815364,
            "bitrate_kbps": 6000
        },
        {
            "time_ms": 288039.92116815364,
            "bitrate_kbps": 2850
        },
        {
            "time_ms": 290408.32140897145,
            "bitrate_kbps": 6000
        },
        {
            "time_ms": 290908.32140897145,
            "bitrate_kbps": 6000
        },
        {
            "time_ms": 291408.32140897145,
            "bitrate_kbps": 2850
        },
        {
            "time_ms": 293997.04605971504,
            "bitrate_kbps": 4300
        },
        {
            "time_ms": 294497.04605971504,
            "bitrate_kbps": 2850
        },
        {
            "time_ms": 297031.7494321807,
            "bitrate_kbps": 2850
        },
        {
            "time_ms": 299553.9443399946,
            "bitrate_kbps": 1850
        },
        {
            "time_ms": 301209.3244158208,
            "bitrate_kbps": 1850
        },
        {
            "time_ms": 302868.66867811594,
            "bitrate_kbps": 1850
        },
        {
            "time_ms": 304528.012940411,
            "bitrate_kbps": 1850
        },
        {
            "time_ms": 306420.1723404916,
            "bitrate_kbps": 1850
        },
        {
            "time_ms": 308400.9566542171,
            "bitrate_kbps": 1850
        },
        {
            "time_ms": 310310.6275146648,
            "bitrate_kbps": 1200
        },
        {
            "time_ms": 311365.5563633064,
            "bitrate_kbps": 1850
        },
        {
            "time_ms": 312981.071671629,
            "bitrate_kbps": 1850
        },
        {
            "time_ms": 314596.58697995153,
            "bitrate_kbps": 1850
        },
        {
            "time_ms": 316216.2982286922,
            "bitrate_kbps": 1850
        },
        {
            "time_ms": 317837.3367401591,
            "bitrate_kbps": 1850
        },
        {
            "time_ms": 319458.37525162596,
            "bitrate_kbps": 1850
        },
        {
            "time_ms": 321305.35070984176,
            "bitrate_kbps": 1850
        },
        {
            "time_ms": 323261.509788858,
            "bitrate_kbps": 1850
        },
        {
            "time_ms": 325016.4849683553,
            "bitrate_kbps": 1850
        },
        {
            "time_ms": 325183.11834528233,
            "bitrate_kbps": 1850
        },
        {
            "time_ms": 325349.7517222094,
            "bitrate_kbps": 2850
        },
        {
            "time_ms": 325595.64638396184,
            "bitrate_kbps": 2850
        },
        {
            "time_ms": 325841.5410457143,
            "bitrate_kbps": 2850
        },
        {
            "time_ms": 326087.43570746674,
            "bitrate_kbps": 4300
        },
        {
            "time_ms": 326448.25923221605,
            "bitrate_kbps": 4300
        },
        {
            "time_ms": 326809.08275696536,
            "bitrate_kbps": 4300
        },
        {
            "time_ms": 327169.9062817147,
            "bitrate_kbps": 6000
        },
        {
            "time_ms": 327665.4739906672,
            "bitrate_kbps": 6000
        },
        {
            "time_ms": 328553.94433999446,
            "bitrate_kbps": 6000
        },
        {
            "time_ms": 330553.94433999446,
            "bitrate_kbps": 6000
        },
        {
            "time_ms": 332553.94433999446,
            "bitrate_kbps": 6000
        },
        {
            "time_ms": 334553.94433999446,
            "bitrate_kbps": 6000
        },
        {
            "time_ms": 336553.94433999446,
            "bitrate_kbps": 9000
        },
        {
            "time_ms": 338553.94433999446,
            "bitrate_kbps": 9000
        },
        {
            "time_ms": 340553.94433999446,
            "bitrate_kbps": 9000
        },
        {
            "time_ms": 342553.94433999446,
            "bitrate_kbps": 9000
        },
        {
            "time_ms": 344553.94433999446,
            "bitrate_kbps": 12000
        },
        {
            "time_ms": 346553.94433999446,
            "bitrate_kbps": 12000
        },
        {
            "time_ms": 348553.94433999446,
            "bitrate_kbps": 12000
        },
        {
            "time_ms": 350553.94433999446,
            "bitrate_kbps": 12000
        },
        {
            "time_ms": 352553.94433999446,
            "bitrate_kbps": 12000
        },
        {
            "time_ms": 354553.94433999446,
            "bitrate_kbps": 12000
        },
        {
            "time_ms": 356553.94433999446,
            "bitrate_kbps": 12000
        },
        {
            "time_ms": 358553.94433999446,
            "bitrate_kbps": 12000
        },
        {
            "time_ms": 360553.94433999446,
            "bitrate_kbps": 12000
        },
        {
            "time_ms": 362553.94433999446,
            "bitrate_kbps": 12000
        },
        {
            "time_ms": 364553.94433999446,
            "bitrate_kbps": 12000
        },
        {
            "time_ms": 366553.94433999446,
            "bitrate_kbps": 12000
        },
        {
            "time_ms": 368553.94433999446,
            "bitrate_kbps": 12000
        },
        {
            "time_ms": 370553.94433999446,
            "bitrate_kbps": 12000
        },
        {
            "time_ms": 372553.94433999446,
            "bitrate_kbps": 12000
        },
        {
            "time_ms": 374553.94433999446,
            "bitrate_kbps": 12000
        },
        {
            "time_ms": 376553.94433999446,
            "bitrate_kbps": 12000
        },
        {
            "time_ms": 378553.94433999446,
            "bitrate_kbps": 12000
        },
        {
            "time_ms": 380553.94433999446,
            "bitrate_kbps": 12000
        },
        {
            "time_ms": 382553.94433999446,
            "bitrate_kbps": 12000
        },
        {
            "time_ms": 384553.94433999446,
            "bitrate_kbps": 12000
        },
        {
            "time_ms": 386553.94433999446,
            "bitrate_kbps": 12000
        },
        {
            "time_ms": 388553.94433999446,
            "bitrate_kbps": 12000
        },
        {
            "time_ms": 390553.94433999446,
            "bitrate_kbps": 12000
        },
        {
            "time_ms": 392553.94433999446,
            "bitrate_kbps": 12000
        },
        {
            "time_ms": 394553.94433999446,
            "bitrate_kbps": 12000
        },
        {
            "time_ms": 396553.94433999446,
            "bitrate_kbps": 12000
        },
        {
            "time_ms": 398553.94433999446,
            "bitrate_kbps": 12000
        },
        {
            "time_ms": 400553.94433999446,
            "bitrate_kbps": 12000
        },
        {
            "time_ms": 402553.94433999446,
            "bitrate_kbps": 12000
        },
        {
            "time_ms": 404553.9443399945,
            "bitrate_kbps": 12000
        },
        {
            "time_ms": 406553.9443399945,
            "bitrate_kbps": 12000
        },
        {
            "time_ms": 408553.9443399945,
            "bitrate_kbps": 12000
        },
        {
            "time_ms": 410553.9443399945,
            "bitrate_kbps": 12000
        },
        {
            "time_ms": 412553.9443399945,
            "bitrate_kbps": 12000
        },
        {
            "time_ms": 414553.9443399945,
            "bitrate_kbps": 12000
        },
        {
            "time_ms": 416553.9443399945,
            "bitrate_kbps": 12000
        },
        {
            "time_ms": 418553.9443399945,
            "bitrate_kbps": 12000
        },
        {
            "time_ms": 420553.9443399945,
            "bitrate_kbps": 12000
        },
        {
            "time_ms": 422553.9443399945,
            "bitrate_kbps": 12000
        },
        {
            "time_ms": 424553.9443399945,
            "bitrate_kbps": 12000
        },
        {
            "time_ms": 426553.9443399945,
            "bitrate_kbps": 12000
        },
        {
            "time_ms": 428553.9443399945,
            "bitrate_kbps": 12000
        },
        {
            "time_ms": 430553.9443399945,
            "bitrate_kbps": 12000
        },
        {
            "time_ms": 432553.9443399945,
            "bitrate_kbps": 12000
        },
        {
            "time_ms": 434553.9443399945,
            "bitrate_kbps": 12000
        },
        {
            "time_ms": 436553.9443399945,
            "bitrate_kbps": 12000
        },
        {
            "time_ms": 438553.9443399945,
            "bitrate_kbps": 12000
        },
        {
            "time_ms": 440553.9443399945,
            "bitrate_kbps": 12000
        },
        {
            "time_ms": 442553.9443399945,
            "bitrate_kbps": 12000
        },
        {
            "time_ms": 444553.9443399945,
            "bitrate_kbps": 12000
        },
        {
            "time_ms": 446003.9443399945,
            "bitrate_kbps": 12000
        },
        {
            "time_ms": 446503.9443399945,
            "bitrate_kbps": 12000
        },
        {
            "time_ms": 447003.9443399945,
            "bitrate_kbps": 12000
        },
        {
            "time_ms": 447503.9443399945,
            "bitrate_kbps": 12000
        },
        {
            "time_ms": 448003.9443399945,
            "bitrate_kbps": 12000
        },
        {
            "time_ms": 448503.9443399945,
            "bitrate_kbps": 12000
        },
        {
            "time_ms": 449003.9443399945,
            "bitrate_kbps": 12000
        },
        {
            "time_ms": 449503.9443399945,
            "bitrate_kbps": 12000
        },
        {
            "time_ms": 450003.9443399945,
            "bitrate_kbps": 12000
        },
        {
            "time_ms": 450503.9443399945,
            "bitrate_kbps": 12000
        },
        {
            "time_ms": 451003.9443399945,
            "bitrate_kbps": 12000
        },
        {
            "time_ms": 451503.9443399945,
            "bitrate_kbps": 12000
        },
        {
            "time_ms": 452003.9443399945,
            "bitrate_kbps": 12000
        },
        {
            "time_ms": 452503.9443399945,
            "bitrate_kbps": 12000
        },
        {
            "time_ms": 453003.9443399945,
            "bitrate_kbps": 12000
        },
        {
            "time_ms": 453503.9443399945,
            "bitrate_kbps": 12000
        },
        {
            "time_ms": 454003.9443399945,
            "bitrate_kbps": 12000
        },
        {
            "time_ms": 454503.9443399945,
            "bitrate_kbps": 12000
        },
        {
            "time_ms": 455003.9443399945,
            "bitrate_kbps": 12000
        },
        {
            "time_ms": 455503.9443399945,
            "bitrate_kbps": 12000
        },
        {
            "time_ms": 456003.9443399945,
            "bitrate_kbps": 12000
        },
        {
            "time_ms": 456503.9443399945,
            "bitrate_kbps": 12000
        },
        {
            "time_ms": 457003.9443399945,
            "bitrate_kbps": 12000
        },
        {
            "time_ms": 457503.9443399945,
            "bitrate_kbps": 12000
        },
        {
            "time_ms": 458003.9443399945,
            "bitrate_kbps": 12000
        },
        {
            "time_ms": 458503.9443399945,
            "bitrate_kbps": 12000
        },
        {
            "time_ms": 459003.9443399945,
            "bitrate_kbps": 12000
        },
        {
            "time_ms": 459503.9443399945,
            "bitrate_kbps": 12000
        },
        {
            "time_ms": 460003.9443399945,
            "bitrate_kbps": 12000
        },
        {
            "time_ms": 460503.9443399945,
            "bitrate_kbps": 12000
        },
        {
            "time_ms": 461003.9443399945,
            "bitrate_kbps": 12000
        },
        {
            "time_ms": 461503.9443399945,
            "bitrate_kbps": 12000
        },
        {
            "time_ms": 462003.9443399945,
            "bitrate_kbps": 12000
        },
        {
            "time_ms": 462503.9443399945,
            "bitrate_kbps": 12000
        },
        {
            "time_ms": 463003.9443399945,
            "bitrate_kbps": 12000
        },
        {
            "time_ms": 463503.9443399945,
            "bitrate_kbps": 12000
        },
        {
            "time_ms": 464003.9443399945,
            "bitrate_kbps": 12000
        },
        {
            "time_ms": 464503.9443399945,
            "bitrate_kbps": 12000
        },
        {
            "time_ms": 465003.9443399945,
            "bitrate_kbps": 12000
        },
        {
            "time_ms": 465503.9443399945,
            "bitrate_kbps": 12000
        },
        {
            "time_ms": 466003.9443399945,
            "bitrate_kbps": 9000
        },
        {
            "time_ms": 466503.9443399945,
            "bitrate_kbps": 6000
        },
        {
            "time_ms": 467003.9443399945,
            "bitrate_kbps": 2850
        },
        {
            "time_ms": 467503.9443399945,
            "bitrate_kbps": 150
        },
        {
            "time_ms": 467775.6221923435,
            "bitrate_kbps": 12000
        },
        {
            "time_ms": 468275.6221923435,
            "bitrate_kbps": 9000
        },
        {
            "time_ms": 468775.6221923435,
            "bitrate_kbps": 6000
        },
        {
            "time_ms": 469275.6221923435,
            "bitrate_kbps": 2850
        },
        {
            "time_ms": 469775.6221923435,
            "bitrate_kbps": 150
        },
        {
            "time_ms": 470048.6468104172,
            "bitrate_kbps": 12000
        },
        {
            "time_ms": 470548.6468104172,
            "bitrate_kbps": 9000
        },
        {
            "time_ms": 471048.6468104172,
            "bitrate_kbps": 6000
        },
        {
            "time_ms": 471548.6468104172,
            "bitrate_kbps": 2850
        },
        {
            "time_ms": 472048.6468104172,
            "bitrate_kbps": 150
        },
        {
            "time_ms": 472327.49064130586,
            "bitrate_kbps": 12000
        },
        {
            "time_ms": 472827.49064130586,
            "bitrate_kbps": 9000
        },
        {
            "time_ms": 473327.49064130586,
            "bitrate_kbps": 6000
        },
        {
            "time_ms": 473827.49064130586,
            "bitrate_kbps": 2850
        },
        {
            "time_ms": 474327.49064130586,
            "bitrate_kbps": 150
        },
        {
            "time_ms": 474606.33447219455,
            "bitrate_kbps": 9000
        },
        {
            "time_ms": 475106.33447219455,
            "bitrate_kbps": 6000
        },
        {
            "time_ms": 475606.33447219455,
            "bitrate_kbps": 4300
        },
        {
            "time_ms": 476106.33447219455,
            "bitrate_kbps": 1850
        },
        {
            "time_ms": 479636.7709048321,
            "bitrate_kbps": 4300
        },
        {
            "time_ms": 480136.7709048321,
            "bitrate_kbps": 2850
        },
        {
            "time_ms": 480636.7709048321,
            "bitrate_kbps": 1850
        },
        {
            "time_ms": 483896.7008522927,
            "bitrate_kbps": 2850
        },
        {
            "time_ms": 484396.7008522927,
            "bitrate_kbps": 1850
        },
        {
            "time_ms": 487624.45707034454,
            "bitrate_kbps": 1200
        },
        {
            "time_ms": 489720.5816378186,
            "bitrate_kbps": 1200
        },
        {
            "time_ms": 492034.99260980455,
            "bitrate_kbps": 750
        },
        {
            "time_ms": 493508.48098189756,
            "bitrate_kbps": 750
        },
        {
            "time_ms": 494981.96935399063,
            "bitrate_kbps": 750
        },
        {
            "time_ms": 496295.07280226646,
            "bitrate_kbps": 1200
        },
        {
            "time_ms": 498384.03831950785,
            "bitrate_kbps": 750
        },
        {
            "time_ms": 499697.14176778373,
            "bitrate_kbps": 750
        },
        {
            "time_ms": 501031.58842484956,
            "bitrate_kbps": 750
        },
        {
            "time_ms": 502372.0109600608,
            "bitrate_kbps": 750
        },
        {
            "time_ms": 503712.43349527207,
            "bitrate_kbps": 750
        },
        {
            "time_ms": 505002.24961412576,
            "bitrate_kbps": 750
        },
        {
            "time_ms": 505078.448332795,
            "bitrate_kbps": 1200
        },
        {
            "time_ms": 505188.36628266575,
            "bitrate_kbps": 1200
        },
        {
            "time_ms": 505298.2842325365,
            "bitrate_kbps": 1850
        },
        {
            "time_ms": 505456.90773858724,
            "bitrate_kbps": 2850
        },
        {
            "time_ms": 505690.46286953025,
            "bitrate_kbps": 2850
        },
        {
            "time_ms": 505924.01800047327,
            "bitrate_kbps": 4300
        },
        {
            "time_ms": 506266.2239875101,
            "bitrate_kbps": 4300
        },
        {
            "time_ms": 506608.4299745469,
            "bitrate_kbps": 4300
        },
        {
            "time_ms": 507034.99260980455,
            "bitrate_kbps": 6000
        },
        {
            "time_ms": 509034.99260980455,
            "bitrate_kbps": 6000
        },
        {
            "time_ms": 511034.99260980455,
            "bitrate_kbps": 6000
        },
        {
            "time_ms": 513034.99260980455,
            "bitrate_kbps": 6000
        },
        {
            "time_ms": 515034.99260980455,
            "bitrate_kbps": 6000
        },
        {
            "time_ms": 517034.99260980455,
            "bitrate_kbps": 9000
        },
        {
            "time_ms": 519034.99260980455,
            "bitrate_kbps": 9000
        },
        {
            "time_ms": 521034.99260980455,
            "bitrate_kbps": 9000
        },
        {
            "time_ms": 523034.99260980455,
            "bitrate_kbps": 9000
        },
        {
            "time_ms": 525034.9926098046,
            "bitrate_kbps": 12000
        },
        {
            "time_ms": 527034.9926098046,
            "bitrate_kbps": 12000
        },
        {
            "time_ms": 529034.9926098046,
            "bitrate_kbps": 12000
        },
        {
            "time_ms": 531034.9926098046,
            "bitrate_kbps": 12000
        },
        {
            "time_ms": 533034.9926098046,
            "bitrate_kbps": 12000
        },
        {
            "time_ms": 535034.9926098046,
            "bitrate_kbps": 12000
        },
        {
            "time_ms": 537034.9926098046,
            "bitrate_kbps": 12000
        },
        {
            "time_ms": 539034.9926098046,
            "bitrate_kbps": 12000
        },
        {
            "time_ms": 541034.9926098046,
            "bitrate_kbps": 12000
        },
        {
            "time_ms": 543034.9926098046,
            "bitrate_kbps": 12000
        },
        {
            "time_ms": 545034.9926098046,
            "bitrate_kbps": 12000
        },
        {
            "time_ms": 547034.9926098046,
            "bitrate_kbps": 12000
        },
        {
            "time_ms": 549034.9926098046,
            "bitrate_kbps": 12000
        },
        {
            "time_ms": 551034.9926098046,
            "bitrate_kbps": 12000
        },
        {
            "time_ms": 553034.9926098046,
            "bitrate_kbps": 12000
        },
        {
            "time_ms": 555034.9926098046,
            "bitrate_kbps": 12000
        },
        {
            "time_ms": 557034.9926098046,
            "bitrate_kbps": 12000
        },
        {
            "time_ms": 559034.9926098046,
            "bitrate_kbps": 12000
        },
        {
            "time_ms": 561034.9926098046,
            "bitrate_kbps": 12000
        },
        {
            "time_ms": 563034.9926098046,
            "bitrate_kbps": 12000
        },
        {
            "time_ms": 565034.9926098046,
            "bitrate_kbps": 12000
        },
        {
            "time_ms": 567034.9926098046,
            "bitrate_kbps": 12000
        },
        {
            "time_ms": 569034.9926098046,
            "bitrate_kbps": 12000
        },
        {
            "time_ms": 571034.9926098046,
            "bitrate_kbps": 12000
        },
        {
            "time_ms": 573034.9926098046,
            "bitrate_kbps": 12000
        },
        {
            "time_ms": 575034.9926098046,
            "bitrate_kbps": 12000
        },
        {
            "time_ms": 577034.9926098046,
            "bitrate_kbps": 12000
        },
        {
            "time_ms": 579034.9926098046,
            "bitrate_kbps": 12000
        },
        {
            "time_ms": 581034.9926098046,
            "bitrate_kbps": 12000
        },
        {
            "time_ms": 583034.9926098046,
            "bitrate_kbps": 12000
        },
        {
            "time_ms": 585034.9926098046,
            "bitrate_kbps": 12000
        },
        {
            "time_ms": 587034.9926098046,
            "bitrate_kbps": 12000
        },
        {
            "time_ms": 589034.9926098046,
            "bitrate_kbps": 12000
        },
        {
            "time_ms": 591034.9926098046,
            "bitrate_kbps": 12000
        },
        {
            "time_ms": 593034.9926098046,
            "bitrate_kbps": 12000
        }
    ]
}