{
    "traces_file": "./temp_traces/mmsys18_sd_fs_traces_160.json",
    "abr_algorithm": "dynamicdash",
    "manifest_file": "/home/jonathan/prg/ex/sabre/manifests/green_abr_manifest.json",
    "bitrate_choices": [
        {
            "time_ms": 0,
            "bitrate_kbps": 150
        },
        {
            "time_ms": 48.60684657194622,
            "bitrate_kbps": 9000
        },
        {
            "time_ms": 1785.0176408887196,
            "bitrate_kbps": 9000
        },
        {
            "time_ms": 3521.428435205493,
            "bitrate_kbps": 9000
        },
        {
            "time_ms": 5257.986833317432,
            "bitrate_kbps": 9000
        },
        {
            "time_ms": 6995.38021181185,
            "bitrate_kbps": 9000
        },
        {
            "time_ms": 8732.773590306268,
            "bitrate_kbps": 9000
        },
        {
            "time_ms": 10465.855549253167,
            "bitrate_kbps": 9000
        },
        {
            "time_ms": 12187.500472679145,
            "bitrate_kbps": 9000
        },
        {
            "time_ms": 13909.145396105123,
            "bitrate_kbps": 9000
        },
        {
            "time_ms": 15671.277665995975,
            "bitrate_kbps": 9000
        },
        {
            "time_ms": 17502.142857142855,
            "bitrate_kbps": 9000
        },
        {
            "time_ms": 19333.008048289736,
            "bitrate_kbps": 9000
        },
        {
            "time_ms": 21196.617707902355,
            "bitrate_kbps": 6000
        },
        {
            "time_ms": 22457.82581712867,
            "bitrate_kbps": 6000
        },
        {
            "time_ms": 23719.033926354983,
            "bitrate_kbps": 6000
        },
        {
            "time_ms": 24980.242035581297,
            "bitrate_kbps": 6000
        },
        {
            "time_ms": 26165.40370176248,
            "bitrate_kbps": 6000
        },
        {
            "time_ms": 27350.565367943662,
            "bitrate_kbps": 6000
        },
        {
            "time_ms": 28535.727034124844,
            "bitrate_kbps": 6000
        },
        {
            "time_ms": 29720.888700306026,
            "bitrate_kbps": 9000
        },
        {
            "time_ms": 31643.943032859937,
            "bitrate_kbps": 9000
        },
        {
            "time_ms": 33594.030959087686,
            "bitrate_kbps": 9000
        },
        {
            "time_ms": 35508.15669181372,
            "bitrate_kbps": 9000
        },
        {
            "time_ms": 37330.68022475984,
            "bitrate_kbps": 9000
        },
        {
            "time_ms": 39153.20375770597,
            "bitrate_kbps": 9000
        },
        {
            "time_ms": 41017.184750438646,
            "bitrate_kbps": 9000
        },
        {
            "time_ms": 42916.29530477626,
            "bitrate_kbps": 9000
        },
        {
            "time_ms": 44815.405859113875,
            "bitrate_kbps": 9000
        },
        {
            "time_ms": 46664.64146811796,
            "bitrate_kbps": 9000
        },
        {
            "time_ms": 48509.08906592862,
            "bitrate_kbps": 9000
        },
        {
            "time_ms": 50352.32249741937,
            "bitrate_kbps": 9000
        },
        {
            "time_ms": 52190.50431560119,
            "bitrate_kbps": 9000
        },
        {
            "time_ms": 54028.686133783005,
            "bitrate_kbps": 12000
        },
        {
            "time_ms": 56291.01307874739,
            "bitrate_kbps": 9000
        },
        {
            "time_ms": 57904.63857675536,
            "bitrate_kbps": 12000
        },
        {
            "time_ms": 60054.25172082056,
            "bitrate_kbps": 12000
        },
        {
            "time_ms": 62404.3488081992,
            "bitrate_kbps": 9000
        },
        {
            "time_ms": 64171.921623733186,
            "bitrate_kbps": 9000
        },
        {
            "time_ms": 66378.6568919293,
            "bitrate_kbps": 9000
        },
        {
            "time_ms": 68963.12476484568,
            "bitrate_kbps": 9000
        },
        {
            "time_ms": 71073.37477514346,
            "bitrate_kbps": 9000
        },
        {
            "time_ms": 72872.03090162567,
            "bitrate_kbps": 9000
        },
        {
            "time_ms": 74670.68702810789,
            "bitrate_kbps": 9000
        },
        {
            "time_ms": 76447.60053781657,
            "bitrate_kbps": 9000
        },
        {
            "time_ms": 78219.9369864147,
            "bitrate_kbps": 9000
        },
        {
            "time_ms": 79992.27343501283,
            "bitrate_kbps": 12000
        },
        {
            "time_ms": 82367.5236803514,
            "bitrate_kbps": 9000
        },
        {
            "time_ms": 84153.96136435532,
            "bitrate_kbps": 9000
        },
        {
            "time_ms": 97390.84605441161,
            "bitrate_kbps": 750
        },
        {
            "time_ms": 99233.44629742498,
            "bitrate_kbps": 750
        },
        {
            "time_ms": 101120.99531997564,
            "bitrate_kbps": 300
        },
        {
            "time_ms": 101900.48899086172,
            "bitrate_kbps": 750
        },
        {
            "time_ms": 103819.2231680769,
            "bitrate_kbps": 750
        },
        {
            "time_ms": 105703.24041348704,
            "bitrate_kbps": 750
        },
        {
            "time_ms": 107532.64933990441,
            "bitrate_kbps": 750
        },
        {
            "time_ms": 109362.05826632178,
            "bitrate_kbps": 750
        },
        {
            "time_ms": 111248.70581893901,
            "bitrate_kbps": 750
        },
        {
            "time_ms": 113165.03957367984,
            "bitrate_kbps": 300
        },
        {
            "time_ms": 113943.57307557618,
            "bitrate_kbps": 300
        },
        {
            "time_ms": 114722.10657747251,
            "bitrate_kbps": 300
        },
        {
            "time_ms": 115496.8711452707,
            "bitrate_kbps": 300
        },
        {
            "time_ms": 116269.69423184537,
            "bitrate_kbps": 300
        },
        {
            "time_ms": 117042.51731842002,
            "bitrate_kbps": 750
        },
        {
            "time_ms": 118944.57503485665,
            "bitrate_kbps": 750
        },
        {
            "time_ms": 120849.83161559289,
            "bitrate_kbps": 750
        },
        {
            "time_ms": 122759.00038133597,
            "bitrate_kbps": 750
        },
        {
            "time_ms": 124668.16914707904,
            "bitrate_kbps": 750
        },
        {
            "time_ms": 126534.81164556465,
            "bitrate_kbps": 750
        },
        {
            "time_ms": 128393.0469396823,
            "bitrate_kbps": 750
        },
        {
            "time_ms": 130268.38521306381,
            "bitrate_kbps": 750
        },
        {
            "time_ms": 132251.73599840412,
            "bitrate_kbps": 750
        },
        {
            "time_ms": 134235.08678374445,
            "bitrate_kbps": 750
        },
        {
            "time_ms": 136229.70449508686,
            "bitrate_kbps": 750
        },
        {
            "time_ms": 138231.2104396047,
            "bitrate_kbps": 750
        },
        {
            "time_ms": 140223.56129794513,
            "bitrate_kbps": 750
        },
        {
            "time_ms": 142147.1145974375,
            "bitrate_kbps": 750
        },
        {
            "time_ms": 144070.6678969299,
            "bitrate_kbps": 750
        },
        {
            "time_ms": 145080.36995309612,
            "bitrate_kbps": 1200
        },
        {
            "time_ms": 145346.57430270629,
            "bitrate_kbps": 1850
        },
        {
            "time_ms": 145746.13934168863,
            "bitrate_kbps": 1850
        },
        {
            "time_ms": 146145.70438067097,
            "bitrate_kbps": 2850
        },
        {
            "time_ms": 146750.43971099515,
            "bitrate_kbps": 4300
        },
        {
            "time_ms": 147652.67196376497,
            "bitrate_kbps": 6000
        },
        {
            "time_ms": 148903.69371181584,
            "bitrate_kbps": 6000
        },
        {
            "time_ms": 150158.35429470608,
            "bitrate_kbps": 9000
        },
        {
            "time_ms": 152068.31649546206,
            "bitrate_kbps": 9000
        },
        {
            "time_ms": 153978.27869621807,
            "bitrate_kbps": 9000
        },
        {
            "time_ms": 155980.823919163,
            "bitrate_kbps": 9000
        },
        {
            "time_ms": 158087.7804409021,
            "bitrate_kbps": 9000
        },
        {
            "time_ms": 160177.7737407685,
            "bitrate_kbps": 9000
        },
        {
            "time_ms": 162102.9388550784,
            "bitrate_kbps": 9000
        },
        {
            "time_ms": 164028.10396938832,
            "bitrate_kbps": 9000
        },
        {
            "time_ms": 165943.0875709718,
            "bitrate_kbps": 9000
        },
        {
            "time_ms": 167847.9043248985,
            "bitrate_kbps": 9000
        },
        {
            "time_ms": 169752.7210788252,
            "bitrate_kbps": 9000
        },
        {
            "time_ms": 171717.23652666312,
            "bitrate_kbps": 9000
        },
        {
            "time_ms": 173689.93776337392,
            "bitrate_kbps": 9000
        },
        {
            "time_ms": 175661.13283935282,
            "bitrate_kbps": 9000
        },
        {
            "time_ms": 177629.39563835706,
            "bitrate_kbps": 9000
        },
        {
            "time_ms": 179597.65843736127,
            "bitrate_kbps": 9000
        },
        {
            "time_ms": 181499.84929533285,
            "bitrate_kbps": 9000
        },
        {
            "time_ms": 183385.9077651649,
            "bitrate_kbps": 9000
        },
        {
            "time_ms": 185262.6012315096,
            "bitrate_kbps": 9000
        },
        {
            "time_ms": 187084.4030333114,
            "bitrate_kbps": 9000
        },
        {
            "time_ms": 188906.2048351132,
            "bitrate_kbps": 9000
        },
        {
            "time_ms": 190701.53239150968,
            "bitrate_kbps": 9000
        },
        {
            "time_ms": 192457.81096776124,
            "bitrate_kbps": 12000
        },
        {
            "time_ms": 194792.84906943,
            "bitrate_kbps": 9000
        },
        {
            "time_ms": 196723.71002498452,
            "bitrate_kbps": 9000
        },
        {
            "time_ms": 198675.66237016002,
            "bitrate_kbps": 12000
        },
        {
            "time_ms": 201186.76613270366,
            "bitrate_kbps": 9000
        },
        {
            "time_ms": 203009.83134356214,
            "bitrate_kbps": 9000
        },
        {
            "time_ms": 204832.8965544206,
            "bitrate_kbps": 9000
        },
        {
            "time_ms": 207609.13293920152,
            "bitrate_kbps": 9000
        },
        {
            "time_ms": 210302.56896299715,
            "bitrate_kbps": 6000
        },
        {
            "time_ms": 211541.70946894045,
            "bitrate_kbps": 9000
        },
        {
            "time_ms": 213390.42022785541,
            "bitrate_kbps": 9000
        },
        {
            "time_ms": 215240.8191429078,
            "bitrate_kbps": 9000
        },
        {
            "time_ms": 217102.4397690588,
            "bitrate_kbps": 9000
        },
        {
            "time_ms": 218964.06039520982,
            "bitrate_kbps": 9000
        },
        {
            "time_ms": 220823.74260516287,
            "bitrate_kbps": 9000
        },
        {
            "time_ms": 222681.0397369379,
            "bitrate_kbps": 12000
        },
        {
            "time_ms": 225210.98218865602,
            "bitrate_kbps": 9000
        },
        {
            "time_ms": 227802.04346561644,
            "bitrate_kbps": 9000
        },
        {
            "time_ms": 230278.1892553099,
            "bitrate_kbps": 9000
        },
        {
            "time_ms": 232117.6575662368,
            "bitrate_kbps": 9000
        },
        {
            "time_ms": 233957.12587716372,
            "bitrate_kbps": 9000
        },
        {
            "time_ms": 235805.05734015536,
            "bitrate_kbps": 9000
        },
        {
            "time_ms": 237663.85599170302,
            "bitrate_kbps": 9000
        },
        {
            "time_ms": 239522.65464325066,
            "bitrate_kbps": 9000
        },
        {
            "time_ms": 241433.43717434607,
            "bitrate_kbps": 9000
        },
        {
            "time_ms": 243361.4295423766,
            "bitrate_kbps": 9000
        },
        {
            "time_ms": 245278.3856344597,
            "bitrate_kbps": 9000
        },
        {
            "time_ms": 247133.6221760584,
            "bitrate_kbps": 9000
        },
        {
            "time_ms": 248988.8587176571,
            "bitrate_kbps": 9000
        },
        {
            "time_ms": 250906.67903874503,
            "bitrate_kbps": 9000
        },
        {
            "time_ms": 252897.9855769117,
            "bitrate_kbps": 9000
        },
        {
            "time_ms": 254889.2921150784,
            "bitrate_kbps": 9000
        },
        {
            "time_ms": 256837.336432996,
            "bitrate_kbps": 9000
        },
        {
            "time_ms": 258783.29406192817,
            "bitrate_kbps": 9000
        },
        {
            "time_ms": 260795.84146459374,
            "bitrate_kbps": 9000
        },
        {
            "time_ms": 262917.66304329527,
            "bitrate_kbps": 9000
        },
        {
            "time_ms": 265401.1225418514,
            "bitrate_kbps": 9000
        },
        {
            "time_ms": 268251.1225418514,
            "bitrate_kbps": 4300
        },
        {
            "time_ms": 268301.1225418514,
            "bitrate_kbps": 2850
        },
        {
            "time_ms": 275189.5910573293,
            "bitrate_kbps": 750
        },
        {
            "time_ms": 277047.826351447,
            "bitrate_kbps": 750
        },
        {
            "time_ms": 278906.0616455646,
            "bitrate_kbps": 750
        },
        {
            "time_ms": 280726.0376050998,
            "bitrate_kbps": 750
        },
        {
            "time_ms": 282492.25413594965,
            "bitrate_kbps": 750
        },
        {
            "time_ms": 284258.47066679946,
            "bitrate_kbps": 1200
        },
        {
            "time_ms": 287124.35119663575,
            "bitrate_kbps": 750
        },
        {
            "time_ms": 288934.32733028725,
            "bitrate_kbps": 750
        },
        {
            "time_ms": 290731.2148918883,
            "bitrate_kbps": 750
        },
        {
            "time_ms": 292509.71430572186,
            "bitrate_kbps": 750
        },
        {
            "time_ms": 294288.21371955535,
            "bitrate_kbps": 1200
        },
        {
            "time_ms": 297435.94387992023,
            "bitrate_kbps": 750
        },
        {
            "time_ms": 299474.78641020285,
            "bitrate_kbps": 750
        },
        {
            "time_ms": 301346.8578476416,
            "bitrate_kbps": 750
        },
        {
            "time_ms": 303163.26503327035,
            "bitrate_kbps": 750
        },
        {
            "time_ms": 304979.67221889907,
            "bitrate_kbps": 750
        },
        {
            "time_ms": 306789.64952599135,
            "bitrate_kbps": 750
        },
        {
            "time_ms": 308599.62565964286,
            "bitrate_kbps": 750
        },
        {
            "time_ms": 310412.5556523807,
            "bitrate_kbps": 750
        },
        {
            "time_ms": 312235.4402677653,
            "bitrate_kbps": 1200
        },
        {
            "time_ms": 315137.7379465493,
            "bitrate_kbps": 750
        },
        {
            "time_ms": 316930.7875919394,
            "bitrate_kbps": 750
        },
        {
            "time_ms": 318723.83723732946,
            "bitrate_kbps": 750
        },
        {
            "time_ms": 320519.3424023524,
            "bitrate_kbps": 750
        },
        {
            "time_ms": 322320.8150864379,
            "bitrate_kbps": 1200
        },
        {
            "time_ms": 325016.30038509174,
            "bitrate_kbps": 750
        },
        {
            "time_ms": 325188.199119269,
            "bitrate_kbps": 1200
        },
        {
            "time_ms": 325451.23709395254,
            "bitrate_kbps": 1850
        },
        {
            "time_ms": 325845.92063825636,
            "bitrate_kbps": 2850
        },
        {
            "time_ms": 326443.1358281298,
            "bitrate_kbps": 2850
        },
        {
            "time_ms": 327040.3510180032,
            "bitrate_kbps": 4300
        },
        {
            "time_ms": 328390.84605441167,
            "bitrate_kbps": 6000
        },
        {
            "time_ms": 330390.84605441167,
            "bitrate_kbps": 6000
        },
        {
            "time_ms": 332390.84605441167,
            "bitrate_kbps": 9000
        },
        {
            "time_ms": 334668.4655201084,
            "bitrate_kbps": 9000
        },
        {
            "time_ms": 336673.2595267793,
            "bitrate_kbps": 9000
        },
        {
            "time_ms": 338634.37890562107,
            "bitrate_kbps": 9000
        },
        {
            "time_ms": 340657.93585033057,
            "bitrate_kbps": 9000
        },
        {
            "time_ms": 342822.5801968098,
            "bitrate_kbps": 6000
        },
        {
            "time_ms": 344390.8460544116,
            "bitrate_kbps": 9000
        },
        {
            "time_ms": 346494.75966735475,
            "bitrate_kbps": 9000
        },
        {
            "time_ms": 348575.6710481654,
            "bitrate_kbps": 9000
        },
        {
            "time_ms": 350572.0860868592,
            "bitrate_kbps": 9000
        },
        {
            "time_ms": 352390.8460544116,
            "bitrate_kbps": 9000
        },
        {
            "time_ms": 354390.8460544116,
            "bitrate_kbps": 9000
        },
        {
            "time_ms": 356390.8460544116,
            "bitrate_kbps": 9000
        },
        {
            "time_ms": 358390.8460544116,
            "bitrate_kbps": 9000
        },
        {
            "time_ms": 360390.8460544116,
            "bitrate_kbps": 9000
        },
        {
            "time_ms": 362448.19749753556,
            "bitrate_kbps": 9000
        },
        {
            "time_ms": 364505.5489406595,
            "bitrate_kbps": 9000
        },
        {
            "time_ms": 366528.3038063892,
            "bitrate_kbps": 9000
        },
        {
            "time_ms": 368540.5561583538,
            "bitrate_kbps": 9000
        },
        {
            "time_ms": 370539.49285922735,
            "bitrate_kbps": 9000
        },
        {
            "time_ms": 372503.75727918843,
            "bitrate_kbps": 9000
        },
        {
            "time_ms": 374468.02169914957,
            "bitrate_kbps": 9000
        },
        {
            "time_ms": 376390.8460544116,
            "bitrate_kbps": 9000
        },
        {
            "time_ms": 378390.8460544116,
            "bitrate_kbps": 9000
        },
        {
            "time_ms": 380545.84661705134,
            "bitrate_kbps": 9000
        },
        {
            "time_ms": 384235.5713876935,
            "bitrate_kbps": 6000
        },
        {
            "time_ms": 385867.20449326234,
            "bitrate_kbps": 6000
        },
        {
            "time_ms": 387133.6987282265,
            "bitrate_kbps": 9000
        },
        {
            "time_ms": 389023.44008067274,
            "bitrate_kbps": 9000
        },
        {
            "time_ms": 390891.3310003687,
            "bitrate_kbps": 9000
        },
        {
            "time_ms": 392736.3335350944,
            "bitrate_kbps": 9000
        },
        {
            "time_ms": 394581.33606982016,
            "bitrate_kbps": 9000
        },
        {
            "time_ms": 396765.78105392697,
            "bitrate_kbps": 9000
        },
        {
            "time_ms": 399045.10074766364,
            "bitrate_kbps": 9000
        },
        {
            "time_ms": 401045.4431444205,
            "bitrate_kbps": 9000
        },
        {
            "time_ms": 402848.8573919188,
            "bitrate_kbps": 9000
        },
        {
            "time_ms": 404652.27163941704,
            "bitrate_kbps": 9000
        },
        {
            "time_ms": 406390.84605441155,
            "bitrate_kbps": 9000
        },
        {
            "time_ms": 408390.84605441155,
            "bitrate_kbps": 12000
        },
        {
            "time_ms": 410628.4177107004,
            "bitrate_kbps": 12000
        },
        {
            "time_ms": 413227.12191183935,
            "bitrate_kbps": 9000
        },
        {
            "time_ms": 415188.96700666763,
            "bitrate_kbps": 9000
        },
        {
            "time_ms": 417226.4518755311,
            "bitrate_kbps": 9000
        },
        {
            "time_ms": 419263.93674439465,
            "bitrate_kbps": 9000
        },
        {
            "time_ms": 423738.3398691208,
            "bitrate_kbps": 6000
        },
        {
            "time_ms": 427010.22059577616,
            "bitrate_kbps": 4300
        },
        {
            "time_ms": 429153.1532050084,
            "bitrate_kbps": 4300
        },
        {
            "time_ms": 430616.466318362,
            "bitrate_kbps": 4300
        },
        {
            "time_ms": 431646.21153381345,
            "bitrate_kbps": 6000
        },
        {
            "time_ms": 433075.15834607126,
            "bitrate_kbps": 6000
        },
        {
            "time_ms": 434504.10515832907,
            "bitrate_kbps": 6000
        },
        {
            "time_ms": 435869.2631408323,
            "bitrate_kbps": 9000
        },
        {
            "time_ms": 437858.1977284499,
            "bitrate_kbps": 9000
        },
        {
            "time_ms": 439847.13231606747,
            "bitrate_kbps": 9000
        },
        {
            "time_ms": 441706.345799887,
            "bitrate_kbps": 9000
        },
        {
            "time_ms": 443556.1719664012,
            "bitrate_kbps": 9000
        },
        {
            "time_ms": 449660.21427478327,
            "bitrate_kbps": 4300
        },
        {
            "time_ms": 449710.21427478327,
            "bitrate_kbps": 2850
        },
        {
            "time_ms": 456380.7615787131,
            "bitrate_kbps": 750
        },
        {
            "time_ms": 458203.6461940977,
            "bitrate_kbps": 750
        },
        {
            "time_ms": 460024.8576953708,
            "bitrate_kbps": 750
        },
        {
            "time_ms": 461734.04688456,
            "bitrate_kbps": 1200
        },
        {
            "time_ms": 464456.7495872627,
            "bitrate_kbps": 750
        },
        {
            "time_ms": 466164.627259268,
            "bitrate_kbps": 750
        },
        {
            "time_ms": 467871.9163481319,
            "bitrate_kbps": 750
        },
        {
            "time_ms": 469579.20543699584,
            "bitrate_kbps": 1200
        },
        {
            "time_ms": 472427.18958846707,
            "bitrate_kbps": 750
        },
        {
            "time_ms": 474228.6622725526,
            "bitrate_kbps": 750
        },
        {
            "time_ms": 476037.52826972405,
            "bitrate_kbps": 750
        },
        {
            "time_ms": 477851.7866429298,
            "bitrate_kbps": 750
        },
        {
            "time_ms": 479666.0450161355,
            "bitrate_kbps": 1200
        },
        {
            "time_ms": 482838.69008431514,
            "bitrate_kbps": 750
        },
        {
            "time_ms": 484850.72195682506,
            "bitrate_kbps": 750
        },
        {
            "time_ms": 486696.07452658925,
            "bitrate_kbps": 750
        },
        {
            "time_ms": 488529.8592907972,
            "bitrate_kbps": 750
        },
        {
            "time_ms": 490372.1950909521,
            "bitrate_kbps": 750
        },
        {
            "time_ms": 492248.6307345164,
            "bitrate_kbps": 750
        },
        {
            "time_ms": 494125.0663780808,
            "bitrate_kbps": 750
        },
        {
            "time_ms": 495995.34272261907,
            "bitrate_kbps": 750
        },
        {
            "time_ms": 497860.36117280356,
            "bitrate_kbps": 750
        },
        {
            "time_ms": 499725.37962298805,
            "bitrate_kbps": 1200
        },
        {
            "time_ms": 502461.2723159251,
            "bitrate_kbps": 750
        },
        {
            "time_ms": 504164.7739994268,
            "bitrate_kbps": 750
        },
        {
            "time_ms": 505077.0628183573,
            "bitrate_kbps": 1200
        },
        {
            "time_ms": 505336.13045457605,
            "bitrate_kbps": 1850
        },
        {
            "time_ms": 505724.6930604133,
            "bitrate_kbps": 1850
        },
        {
            "time_ms": 506113.25566625054,
            "bitrate_kbps": 2850
        },
        {
            "time_ms": 506701.0413022701,
            "bitrate_kbps": 4300
        },
        {
            "time_ms": 507577.70033205394,
            "bitrate_kbps": 6000
        },
        {
            "time_ms": 508793.0385131477,
            "bitrate_kbps": 6000
        },
        {
            "time_ms": 510390.8460544116,
            "bitrate_kbps": 9000
        },
        {
            "time_ms": 512390.8460544116,
            "bitrate_kbps": 9000
        },
        {
            "time_ms": 514390.8460544116,
            "bitrate_kbps": 9000
        },
        {
            "time_ms": 516390.8460544116,
            "bitrate_kbps": 9000
        },
        {
            "time_ms": 518390.8460544116,
            "bitrate_kbps": 9000
        },
        {
            "time_ms": 520390.8460544116,
            "bitrate_kbps": 9000
        },
        {
            "time_ms": 522390.8460544116,
            "bitrate_kbps": 9000
        },
        {
            "time_ms": 524390.8460544116,
            "bitrate_kbps": 9000
        },
        {
            "time_ms": 526390.8460544116,
            "bitrate_kbps": 9000
        },
        {
            "time_ms": 528390.8460544116,
            "bitrate_kbps": 9000
        },
        {
            "time_ms": 530390.8460544116,
            "bitrate_kbps": 9000
        },
        {
            "time_ms": 532390.8460544116,
            "bitrate_kbps": 9000
        },
        {
            "time_ms": 534390.8460544116,
            "bitrate_kbps": 9000
        },
        {
            "time_ms": 536390.8460544116,
            "bitrate_kbps": 9000
        },
        {
            "time_ms": 538390.8460544116,
            "bitrate_kbps": 9000
        },
        {
            "time_ms": 540390.8460544116,
            "bitrate_kbps": 12000
        },
        {
            "time_ms": 542954.8358784523,
            "bitrate_kbps": 9000
        },
        {
            "time_ms": 544882.8282464829,
            "bitrate_kbps": 9000
        },
        {
            "time_ms": 550395.472098995,
            "bitrate_kbps": 4300
        },
        {
            "time_ms": 551290.1669728762,
            "bitrate_kbps": 6000
        },
        {
            "time_ms": 552530.6714480593,
            "bitrate_kbps": 6000
        },
        {
            "time_ms": 553771.1759232424,
            "bitrate_kbps": 9000
        },
        {
            "time_ms": 555627.9360933785,
            "bitrate_kbps": 9000
        },
        {
            "time_ms": 557496.3649288682,
            "bitrate_kbps": 9000
        },
        {
            "time_ms": 559364.793764358,
            "bitrate_kbps": 9000
        },
        {
            "time_ms": 561209.6214421152,
            "bitrate_kbps": 9000
        },
        {
            "time_ms": 563042.675430834,
            "bitrate_kbps": 9000
        },
        {
            "time_ms": 564875.7294195527,
            "bitrate_kbps": 9000
        },
        {
            "time_ms": 566646.748367047,
            "bitrate_kbps": 9000
        },
        {
            "time_ms": 568413.9819139312,
            "bitrate_kbps": 12000
        },
        {
            "time_ms": 570773.9946553836,
            "bitrate_kbps": 9000
        },
        {
            "time_ms": 572564.9509717944,
            "bitrate_kbps": 9000
        },
        {
            "time_ms": 574390.8460544116,
            "bitrate_kbps": 12000
        },
        {
            "time_ms": 576910.8677378569,
            "bitrate_kbps": 9000
        }
    ]
}