{
    "traces_file": "./temp_traces/mmsys18_sd_fs_traces_273.json",
    "abr_algorithm": "bolae",
    "manifest_file": "/home/jonathan/prg/ex/sabre/manifests/green_abr_manifest.json",
    "bitrate_choices": [
        {
            "time_ms": 0,
            "bitrate_kbps": 150
        },
        {
            "time_ms": 354.82142857142856,
            "bitrate_kbps": 750
        },
        {
            "time_ms": 2048.9285714285716,
            "bitrate_kbps": 750
        },
        {
            "time_ms": 3743.035714285714,
            "bitrate_kbps": 750
        },
        {
            "time_ms": 5438.120805369127,
            "bitrate_kbps": 750
        },
        {
            "time_ms": 7135.973154362416,
            "bitrate_kbps": 750
        },
        {
            "time_ms": 8833.825503355703,
            "bitrate_kbps": 750
        },
        {
            "time_ms": 10549.50289017341,
            "bitrate_kbps": 750
        },
        {
            "time_ms": 12303.606936416185,
            "bitrate_kbps": 750
        },
        {
            "time_ms": 14057.71098265896,
            "bitrate_kbps": 750
        },
        {
            "time_ms": 15779.37846836848,
            "bitrate_kbps": 750
        },
        {
            "time_ms": 17464.195338512764,
            "bitrate_kbps": 750
        },
        {
            "time_ms": 19149.012208657048,
            "bitrate_kbps": 750
        },
        {
            "time_ms": 20907.34299516908,
            "bitrate_kbps": 750
        },
        {
            "time_ms": 22738.937198067633,
            "bitrate_kbps": 750
        },
        {
            "time_ms": 24570.53140096618,
            "bitrate_kbps": 750
        },
        {
            "time_ms": 26370.672963400237,
            "bitrate_kbps": 750
        },
        {
            "time_ms": 28161.6292798111,
            "bitrate_kbps": 750
        },
        {
            "time_ms": 29952.585596221958,
            "bitrate_kbps": 750
        },
        {
            "time_ms": 31823.185185185182,
            "bitrate_kbps": 750
        },
        {
            "time_ms": 33695.03703703704,
            "bitrate_kbps": 750
        },
        {
            "time_ms": 35555.235792019346,
            "bitrate_kbps": 750
        },
        {
            "time_ms": 37389.020556227326,
            "bitrate_kbps": 750
        },
        {
            "time_ms": 39222.805320435305,
            "bitrate_kbps": 750
        },
        {
            "time_ms": 41065.60975609756,
            "bitrate_kbps": 750
        },
        {
            "time_ms": 42914.87804878049,
            "bitrate_kbps": 750
        },
        {
            "time_ms": 44764.14634146341,
            "bitrate_kbps": 750
        },
        {
            "time_ms": 46567.5355450237,
            "bitrate_kbps": 750
        },
        {
            "time_ms": 48364.78672985782,
            "bitrate_kbps": 750
        },
        {
            "time_ms": 50165.569007263926,
            "bitrate_kbps": 750
        },
        {
            "time_ms": 52001.54963680388,
            "bitrate_kbps": 750
        },
        {
            "time_ms": 53837.530266343834,
            "bitrate_kbps": 750
        },
        {
            "time_ms": 55675.14563106797,
            "bitrate_kbps": 750
        },
        {
            "time_ms": 57515.53398058253,
            "bitrate_kbps": 750
        },
        {
            "time_ms": 59355.92233009709,
            "bitrate_kbps": 1200
        },
        {
            "time_ms": 60199.08783783784,
            "bitrate_kbps": 1200
        },
        {
            "time_ms": 60472.46621621621,
            "bitrate_kbps": 1850
        },
        {
            "time_ms": 60883.09121621621,
            "bitrate_kbps": 2850
        },
        {
            "time_ms": 61504.86486486486,
            "bitrate_kbps": 4300
        },
        {
            "time_ms": 62432.804054054046,
            "bitrate_kbps": 4300
        },
        {
            "time_ms": 63360.74324324323,
            "bitrate_kbps": 6000
        },
        {
            "time_ms": 64647.635135135126,
            "bitrate_kbps": 6000
        },
        {
            "time_ms": 66048.17525162817,
            "bitrate_kbps": 9000
        },
        {
            "time_ms": 68199.61397276494,
            "bitrate_kbps": 6000
        },
        {
            "time_ms": 69640.57312018945,
            "bitrate_kbps": 9000
        },
        {
            "time_ms": 71901.67630057802,
            "bitrate_kbps": 9000
        },
        {
            "time_ms": 74183.55114350338,
            "bitrate_kbps": 6000
        },
        {
            "time_ms": 75583.99793708096,
            "bitrate_kbps": 9000
        },
        {
            "time_ms": 77460.6250644662,
            "bitrate_kbps": 9000
        },
        {
            "time_ms": 79337.25219185147,
            "bitrate_kbps": 9000
        },
        {
            "time_ms": 81314.6291331546,
            "bitrate_kbps": 9000
        },
        {
            "time_ms": 83345.35299374441,
            "bitrate_kbps": 9000
        },
        {
            "time_ms": 85373.78039302764,
            "bitrate_kbps": 9000
        },
        {
            "time_ms": 87392.22604640834,
            "bitrate_kbps": 9000
        },
        {
            "time_ms": 89410.67169978905,
            "bitrate_kbps": 9000
        },
        {
            "time_ms": 91453.6487859966,
            "bitrate_kbps": 9000
        },
        {
            "time_ms": 93506.39864483342,
            "bitrate_kbps": 9000
        },
        {
            "time_ms": 95540.76671035386,
            "bitrate_kbps": 9000
        },
        {
            "time_ms": 97526.69069462646,
            "bitrate_kbps": 9000
        },
        {
            "time_ms": 99512.61467889907,
            "bitrate_kbps": 9000
        },
        {
            "time_ms": 101570.58379120879,
            "bitrate_kbps": 9000
        },
        {
            "time_ms": 103651.02335164834,
            "bitrate_kbps": 9000
        },
        {
            "time_ms": 105678.42233782778,
            "bitrate_kbps": 9000
        },
        {
            "time_ms": 107609.45323282726,
            "bitrate_kbps": 9000
        },
        {
            "time_ms": 109540.48412782673,
            "bitrate_kbps": 9000
        },
        {
            "time_ms": 111620.31797989244,
            "bitrate_kbps": 9000
        },
        {
            "time_ms": 113744.59667991582,
            "bitrate_kbps": 9000
        },
        {
            "time_ms": 115785.74479331852,
            "bitrate_kbps": 9000
        },
        {
            "time_ms": 117708.69436515486,
            "bitrate_kbps": 9000
        },
        {
            "time_ms": 119631.64393699121,
            "bitrate_kbps": 9000
        },
        {
            "time_ms": 121546.74450404964,
            "bitrate_kbps": 9000
        },
        {
            "time_ms": 123460.08625223518,
            "bitrate_kbps": 9000
        },
        {
            "time_ms": 125374.37308868501,
            "bitrate_kbps": 9000
        },
        {
            "time_ms": 127292.50659074132,
            "bitrate_kbps": 9000
        },
        {
            "time_ms": 129210.64009279764,
            "bitrate_kbps": 9000
        },
        {
            "time_ms": 131215.13906232262,
            "bitrate_kbps": 9000
        },
        {
            "time_ms": 133278.5038029288,
            "bitrate_kbps": 9000
        },
        {
            "time_ms": 135313.08036178397,
            "bitrate_kbps": 9000
        },
        {
            "time_ms": 137204.37675434037,
            "bitrate_kbps": 9000
        },
        {
            "time_ms": 139095.67314689676,
            "bitrate_kbps": 9000
        },
        {
            "time_ms": 140976.41262984675,
            "bitrate_kbps": 9000
        },
        {
            "time_ms": 142847.6930988378,
            "bitrate_kbps": 9000
        },
        {
            "time_ms": 144718.97356782886,
            "bitrate_kbps": 9000
        },
        {
            "time_ms": 146537.4405886447,
            "bitrate_kbps": 9000
        },
        {
            "time_ms": 148347.2387391866,
            "bitrate_kbps": 12000
        },
        {
            "time_ms": 150895.7948233069,
            "bitrate_kbps": 9000
        },
        {
            "time_ms": 153043.20293109558,
            "bitrate_kbps": 9000
        },
        {
            "time_ms": 155173.5643564356,
            "bitrate_kbps": 9000
        },
        {
            "time_ms": 157130.7145931984,
            "bitrate_kbps": 9000
        },
        {
            "time_ms": 159087.8648299612,
            "bitrate_kbps": 9000
        },
        {
            "time_ms": 161001.36949572028,
            "bitrate_kbps": 9000
        },
        {
            "time_ms": 162877.61369495717,
            "bitrate_kbps": 9000
        },
        {
            "time_ms": 164753.85789419405,
            "bitrate_kbps": 9000
        },
        {
            "time_ms": 166757.71155343042,
            "bitrate_kbps": 9000
        },
        {
            "time_ms": 168779.26831980425,
            "bitrate_kbps": 9000
        },
        {
            "time_ms": 170714.18286394284,
            "bitrate_kbps": 9000
        },
        {
            "time_ms": 172519.18881396268,
            "bitrate_kbps": 12000
        },
        {
            "time_ms": 174919.19674732245,
            "bitrate_kbps": 9000
        },
        {
            "time_ms": 176788.95565387383,
            "bitrate_kbps": 9000
        },
        {
            "time_ms": 178660.9980450663,
            "bitrate_kbps": 9000
        },
        {
            "time_ms": 197161.52823920263,
            "bitrate_kbps": 300
        },
        {
            "time_ms": 199174.8837209302,
            "bitrate_kbps": 300
        },
        {
            "time_ms": 201184.30463576157,
            "bitrate_kbps": 300
        },
        {
            "time_ms": 203191.05960264898,
            "bitrate_kbps": 300
        },
        {
            "time_ms": 205197.1617161716,
            "bitrate_kbps": 300
        },
        {
            "time_ms": 207197.35973597356,
            "bitrate_kbps": 150
        },
        {
            "time_ms": 208207.45874587455,
            "bitrate_kbps": 150
        },
        {
            "time_ms": 209217.55775577555,
            "bitrate_kbps": 150
        },
        {
            "time_ms": 210228.41059602646,
            "bitrate_kbps": 150
        },
        {
            "time_ms": 211241.78807947016,
            "bitrate_kbps": 150
        },
        {
            "time_ms": 212255.16556291387,
            "bitrate_kbps": 150
        },
        {
            "time_ms": 213268.54304635758,
            "bitrate_kbps": 150
        },
        {
            "time_ms": 214281.92052980128,
            "bitrate_kbps": 150
        },
        {
            "time_ms": 215294.32343234317,
            "bitrate_kbps": 150
        },
        {
            "time_ms": 216304.42244224416,
            "bitrate_kbps": 300
        },
        {
            "time_ms": 218304.62046204615,
            "bitrate_kbps": 300
        },
        {
            "time_ms": 220319.58477508646,
            "bitrate_kbps": 300
        },
        {
            "time_ms": 222415.7093425605,
            "bitrate_kbps": 300
        },
        {
            "time_ms": 224511.83391003456,
            "bitrate_kbps": 300
        },
        {
            "time_ms": 226543.85382059796,
            "bitrate_kbps": 300
        },
        {
            "time_ms": 228557.20930232553,
            "bitrate_kbps": 300
        },
        {
            "time_ms": 230566.79867986793,
            "bitrate_kbps": 300
        },
        {
            "time_ms": 232566.99669966992,
            "bitrate_kbps": 300
        },
        {
            "time_ms": 234567.19471947188,
            "bitrate_kbps": 300
        },
        {
            "time_ms": 236572.5827814569,
            "bitrate_kbps": 300
        },
        {
            "time_ms": 238579.33774834432,
            "bitrate_kbps": 300
        },
        {
            "time_ms": 240015.89154246717,
            "bitrate_kbps": 300
        },
        {
            "time_ms": 240089.76117794932,
            "bitrate_kbps": 300
        },
        {
            "time_ms": 240163.63081343146,
            "bitrate_kbps": 750
        },
        {
            "time_ms": 240318.3049021368,
            "bitrate_kbps": 750
        },
        {
            "time_ms": 240472.97899084212,
            "bitrate_kbps": 1200
        },
        {
            "time_ms": 240708.45753277067,
            "bitrate_kbps": 1850
        },
        {
            "time_ms": 241354.8214285714,
            "bitrate_kbps": 2850
        },
        {
            "time_ms": 243354.82142857136,
            "bitrate_kbps": 4300
        },
        {
            "time_ms": 245354.82142857136,
            "bitrate_kbps": 4300
        },
        {
            "time_ms": 247354.82142857136,
            "bitrate_kbps": 6000
        },
        {
            "time_ms": 249354.82142857136,
            "bitrate_kbps": 9000
        },
        {
            "time_ms": 251354.82142857136,
            "bitrate_kbps": 9000
        },
        {
            "time_ms": 253354.82142857136,
            "bitrate_kbps": 9000
        },
        {
            "time_ms": 255354.82142857136,
            "bitrate_kbps": 9000
        },
        {
            "time_ms": 257354.82142857136,
            "bitrate_kbps": 9000
        },
        {
            "time_ms": 259354.82142857136,
            "bitrate_kbps": 12000
        },
        {
            "time_ms": 262731.57709374453,
            "bitrate_kbps": 9000
        },
        {
            "time_ms": 265603.214704241,
            "bitrate_kbps": 6000
        },
        {
            "time_ms": 267966.964704241,
            "bitrate_kbps": 6000
        },
        {
            "time_ms": 270158.9467085059,
            "bitrate_kbps": 6000
        },
        {
            "time_ms": 271305.3899639269,
            "bitrate_kbps": 6000
        },
        {
            "time_ms": 272451.83321934793,
            "bitrate_kbps": 9000
        },
        {
            "time_ms": 274161.49810247944,
            "bitrate_kbps": 9000
        },
        {
            "time_ms": 275753.16501263704,
            "bitrate_kbps": 9000
        },
        {
            "time_ms": 277354.82142857136,
            "bitrate_kbps": 12000
        },
        {
            "time_ms": 279354.82142857136,
            "bitrate_kbps": 12000
        },
        {
            "time_ms": 282035.7963326492,
            "bitrate_kbps": 9000
        },
        {
            "time_ms": 284304.39096100646,
            "bitrate_kbps": 9000
        },
        {
            "time_ms": 286106.57787528395,
            "bitrate_kbps": 9000
        },
        {
            "time_ms": 287708.43919877463,
            "bitrate_kbps": 9000
        },
        {
            "time_ms": 289354.82142857136,
            "bitrate_kbps": 12000
        },
        {
            "time_ms": 291472.83846800815,
            "bitrate_kbps": 12000
        },
        {
            "time_ms": 293586.1659865428,
            "bitrate_kbps": 12000
        },
        {
            "time_ms": 295718.0314294667,
            "bitrate_kbps": 9000
        },
        {
            "time_ms": 297354.82142857136,
            "bitrate_kbps": 12000
        },
        {
            "time_ms": 299523.62615594175,
            "bitrate_kbps": 12000
        },
        {
            "time_ms": 301952.7645181522,
            "bitrate_kbps": 9000
        },
        {
            "time_ms": 303832.26865038363,
            "bitrate_kbps": 9000
        },
        {
            "time_ms": 305691.9020421484,
            "bitrate_kbps": 9000
        },
        {
            "time_ms": 307519.49392806925,
            "bitrate_kbps": 12000
        },
        {
            "time_ms": 309949.6164426304,
            "bitrate_kbps": 9000
        },
        {
            "time_ms": 311663.29328343173,
            "bitrate_kbps": 9000
        },
        {
            "time_ms": 313375.02260674,
            "bitrate_kbps": 12000
        },
        {
            "time_ms": 315607.9775652686,
            "bitrate_kbps": 12000
        },
        {
            "time_ms": 317735.6442026621,
            "bitrate_kbps": 9000
        },
        {
            "time_ms": 319354.82142857136,
            "bitrate_kbps": 12000
        },
        {
            "time_ms": 321615.72469440487,
            "bitrate_kbps": 12000
        },
        {
            "time_ms": 323932.8150466254,
            "bitrate_kbps": 9000
        },
        {
            "time_ms": 325794.75474072754,
            "bitrate_kbps": 9000
        },
        {
            "time_ms": 327841.32533293654,
            "bitrate_kbps": 9000
        },
        {
            "time_ms": 329887.8959251455,
            "bitrate_kbps": 9000
        },
        {
            "time_ms": 331354.82142857136,
            "bitrate_kbps": 12000
        },
        {
            "time_ms": 333354.82142857136,
            "bitrate_kbps": 12000
        },
        {
            "time_ms": 335354.82142857136,
            "bitrate_kbps": 12000
        },
        {
            "time_ms": 337354.82142857136,
            "bitrate_kbps": 12000
        },
        {
            "time_ms": 339354.82142857136,
            "bitrate_kbps": 12000
        },
        {
            "time_ms": 341354.82142857136,
            "bitrate_kbps": 12000
        },
        {
            "time_ms": 343354.82142857136,
            "bitrate_kbps": 12000
        },
        {
            "time_ms": 345354.82142857136,
            "bitrate_kbps": 12000
        },
        {
            "time_ms": 347354.82142857136,
            "bitrate_kbps": 12000
        },
        {
            "time_ms": 349354.82142857136,
            "bitrate_kbps": 12000
        },
        {
            "time_ms": 351367.6897121671,
            "bitrate_kbps": 12000
        },
        {
            "time_ms": 353433.20236877666,
            "bitrate_kbps": 12000
        },
        {
            "time_ms": 355473.4927490578,
            "bitrate_kbps": 12000
        },
        {
            "time_ms": 357435.5545713591,
            "bitrate_kbps": 12000
        },
        {
            "time_ms": 359397.6163936605,
            "bitrate_kbps": 12000
        },
        {
            "time_ms": 377437.2006247177,
            "bitrate_kbps": 300
        },
        {
            "time_ms": 378089.4450925786,
            "bitrate_kbps": 750
        },
        {
            "time_ms": 379690.05626223085,
            "bitrate_kbps": 750
        },
        {
            "time_ms": 381362.4509375496,
            "bitrate_kbps": 750
        },
        {
            "time_ms": 383050.9715159701,
            "bitrate_kbps": 750
        },
        {
            "time_ms": 384739.49209439056,
            "bitrate_kbps": 750
        },
        {
            "time_ms": 386428.012672811,
            "bitrate_kbps": 750
        },
        {
            "time_ms": 388116.5332512315,
            "bitrate_kbps": 750
        },
        {
            "time_ms": 389805.05382965197,
            "bitrate_kbps": 1200
        },
        {
            "time_ms": 392453.7455064082,
            "bitrate_kbps": 750
        },
        {
            "time_ms": 394114.88336198806,
            "bitrate_kbps": 750
        },
        {
            "time_ms": 395809.6842384213,
            "bitrate_kbps": 1200
        },
        {
            "time_ms": 398569.4102658186,
            "bitrate_kbps": 750
        },
        {
            "time_ms": 400286.06427798385,
            "bitrate_kbps": 750
        },
        {
            "time_ms": 401929.4409013605,
            "bitrate_kbps": 1200
        },
        {
            "time_ms": 404546.8434987631,
            "bitrate_kbps": 750
        },
        {
            "time_ms": 406177.476866014,
            "bitrate_kbps": 750
        },
        {
            "time_ms": 407803.47258335876,
            "bitrate_kbps": 1200
        },
        {
            "time_ms": 410414.360488552,
            "bitrate_kbps": 750
        },
        {
            "time_ms": 412127.36274588836,
            "bitrate_kbps": 750
        },
        {
            "time_ms": 413840.3650032247,
            "bitrate_kbps": 1200
        },
        {
            "time_ms": 416534.5291311888,
            "bitrate_kbps": 750
        },
        {
            "time_ms": 418210.15827026166,
            "bitrate_kbps": 750
        },
        {
            "time_ms": 419885.7874093345,
            "bitrate_kbps": 1200
        },
        {
            "time_ms": 420221.70913724677,
            "bitrate_kbps": 1200
        },
        {
            "time_ms": 420471.59419471805,
            "bitrate_kbps": 1850
        },
        {
            "time_ms": 420846.00032498623,
            "bitrate_kbps": 2850
        },
        {
            "time_ms": 421411.9773364805,
            "bitrate_kbps": 4300
        },
        {
            "time_ms": 422255.73212575255,
            "bitrate_kbps": 6000
        },
        {
            "time_ms": 423425.15741310886,
            "bitrate_kbps": 6000
        },
        {
            "time_ms": 424594.58270046517,
            "bitrate_kbps": 9000
        },
        {
            "time_ms": 426333.483769951,
            "bitrate_kbps": 9000
        },
        {
            "time_ms": 428070.8771484454,
            "bitrate_kbps": 9000
        },
        {
            "time_ms": 429808.2705269398,
            "bitrate_kbps": 9000
        },
        {
            "time_ms": 431602.54262467666,
            "bitrate_kbps": 9000
        },
        {
            "time_ms": 433403.134176759,
            "bitrate_kbps": 9000
        },
        {
            "time_ms": 435197.077836637,
            "bitrate_kbps": 9000
        },
        {
            "time_ms": 436939.5658749145,
            "bitrate_kbps": 12000
        },
        {
            "time_ms": 439256.21659261786,
            "bitrate_kbps": 9000
        },
        {
            "time_ms": 440965.0881628312,
            "bitrate_kbps": 12000
        },
        {
            "time_ms": 443204.43345596973,
            "bitrate_kbps": 9000
        },
        {
            "time_ms": 444888.9424258236,
            "bitrate_kbps": 12000
        },
        {
            "time_ms": 447139.9631234641,
            "bitrate_kbps": 9000
        },
        {
            "time_ms": 448833.6032908281,
            "bitrate_kbps": 12000
        },
        {
            "time_ms": 451129.43998769537,
            "bitrate_kbps": 9000
        },
        {
            "time_ms": 452891.43166484626,
            "bitrate_kbps": 12000
        },
        {
            "time_ms": 455234.06458223885,
            "bitrate_kbps": 9000
        },
        {
            "time_ms": 456995.88769042544,
            "bitrate_kbps": 9000
        },
        {
            "time_ms": 458757.710798612,
            "bitrate_kbps": 12000
        },
        {
            "time_ms": 461125.40718598856,
            "bitrate_kbps": 9000
        },
        {
            "time_ms": 462927.2325671012,
            "bitrate_kbps": 12000
        },
        {
            "time_ms": 465321.2823348618,
            "bitrate_kbps": 9000
        },
        {
            "time_ms": 467113.6336542789,
            "bitrate_kbps": 9000
        },
        {
            "time_ms": 468905.984973696,
            "bitrate_kbps": 12000
        },
        {
            "time_ms": 471208.33441558434,
            "bitrate_kbps": 9000
        },
        {
            "time_ms": 472889.61729514133,
            "bitrate_kbps": 12000
        },
        {
            "time_ms": 475164.4191592035,
            "bitrate_kbps": 9000
        },
        {
            "time_ms": 477375.5329753934,
            "bitrate_kbps": 9000
        },
        {
            "time_ms": 479586.6467915833,
            "bitrate_kbps": 9000
        },
        {
            "time_ms": 481357.15892233566,
            "bitrate_kbps": 9000
        },
        {
            "time_ms": 483031.26662312594,
            "bitrate_kbps": 9000
        },
        {
            "time_ms": 484705.3743239162,
            "bitrate_kbps": 12000
        },
        {
            "time_ms": 487234.3176725709,
            "bitrate_kbps": 9000
        },
        {
            "time_ms": 489168.396787841,
            "bitrate_kbps": 9000
        },
        {
            "time_ms": 491012.66686783126,
            "bitrate_kbps": 9000
        },
        {
            "time_ms": 492790.8227576535,
            "bitrate_kbps": 12000
        },
        {
            "time_ms": 495147.6330939314,
            "bitrate_kbps": 9000
        },
        {
            "time_ms": 496841.8959532003,
            "bitrate_kbps": 12000
        },
        {
            "time_ms": 499094.2464322255,
            "bitrate_kbps": 9000
        },
        {
            "time_ms": 500777.08895341976,
            "bitrate_kbps": 12000
        },
        {
            "time_ms": 502997.10728690587,
            "bitrate_kbps": 9000
        },
        {
            "time_ms": 504667.12103702046,
            "bitrate_kbps": 12000
        },
        {
            "time_ms": 506928.1449276816,
            "bitrate_kbps": 12000
        },
        {
            "time_ms": 509195.96734971023,
            "bitrate_kbps": 9000
        },
        {
            "time_ms": 510909.4147518754,
            "bitrate_kbps": 12000
        },
        {
            "time_ms": 513196.1317900318,
            "bitrate_kbps": 9000
        },
        {
            "time_ms": 514916.1695686491,
            "bitrate_kbps": 12000
        },
        {
            "time_ms": 517121.92170604586,
            "bitrate_kbps": 9000
        },
        {
            "time_ms": 518779.47629119875,
            "bitrate_kbps": 12000
        },
        {
            "time_ms": 521032.18146487593,
            "bitrate_kbps": 9000
        },
        {
            "time_ms": 522771.8719205939,
            "bitrate_kbps": 12000
        },
        {
            "time_ms": 526408.7672902494,
            "bitrate_kbps": 9000
        },
        {
            "time_ms": 526708.7672902494,
            "bitrate_kbps": 4300
        },
        {
            "time_ms": 530627.615259896,
            "bitrate_kbps": 2850
        },
        {
            "time_ms": 531194.6927145462,
            "bitrate_kbps": 4300
        },
        {
            "time_ms": 532040.1078215622,
            "bitrate_kbps": 6000
        },
        {
            "time_ms": 533211.849831352,
            "bitrate_kbps": 6000
        },
        {
            "time_ms": 534383.5918411418,
            "bitrate_kbps": 9000
        },
        {
            "time_ms": 536123.4413681114,
            "bitrate_kbps": 9000
        },
        {
            "time_ms": 537859.1977307079,
            "bitrate_kbps": 9000
        },
        {
            "time_ms": 539594.9540933043,
            "bitrate_kbps": 9000
        },
        {
            "time_ms": 545294.9540933043,
            "bitrate_kbps": 2850
        },
        {
            "time_ms": 545351.7639092553,
            "bitrate_kbps": 1850
        },
        {
            "time_ms": 545408.5737252062,
            "bitrate_kbps": 750
        },
        {
            "time_ms": 550029.8007190713,
            "bitrate_kbps": 750
        },
        {
            "time_ms": 554651.0277129363,
            "bitrate_kbps": 300
        },
        {
            "time_ms": 556539.8594825539,
            "bitrate_kbps": 300
        },
        {
            "time_ms": 558434.8594825539,
            "bitrate_kbps": 300
        },
        {
            "time_ms": 560327.8106658921,
            "bitrate_kbps": 300
        },
        {
            "time_ms": 562211.1647031591,
            "bitrate_kbps": 300
        },
        {
            "time_ms": 564094.5187404262,
            "bitrate_kbps": 300
        },
        {
            "time_ms": 565987.0690734083,
            "bitrate_kbps": 300
        },
        {
            "time_ms": 567887.946816355,
            "bitrate_kbps": 300
        },
        {
            "time_ms": 569788.8245593017,
            "bitrate_kbps": 300
        },
        {
            "time_ms": 571695.0158315008,
            "bitrate_kbps": 300
        },
        {
            "time_ms": 573601.8082843309,
            "bitrate_kbps": 300
        },
        {
            "time_ms": 575515.0797274434,
            "bitrate_kbps": 300
        },
        {
            "time_ms": 577445.9077529211,
            "bitrate_kbps": 300
        },
        {
            "time_ms": 579376.7357783988,
            "bitrate_kbps": 300
        },
        {
            "time_ms": 581263.3077982069,
            "bitrate_kbps": 300
        },
        {
            "time_ms": 583129.4616443607,
            "bitrate_kbps": 300
        },
        {
            "time_ms": 584995.6154905146,
            "bitrate_kbps": 300
        }
    ]
}